colorcountcython/README.MD
colorcountcython/__init__.py
colorcountcython/requirements.txt
colorcountcython/thirdparty.json
colorcountcython-0.10.dist-info/LICENSE.rst
colorcountcython-0.10.dist-info/METADATA
colorcountcython-0.10.dist-info/WHEEL
colorcountcython-0.10.dist-info/top_level.txt
colorcountcython-0.10.dist-info/RECORD
