Metadata-Version: 2.1
Name: colorcountcython
Version: 0.10
Summary: This module provides functionality to count unique colors in an image represented as a NumPy array and, optionally, group their coordinates. It includes a Cython-based implementation for improved performance.
Home-page: https://github.com/hansalemaos/colorcountcython
Author: Johannes Fischer
Author-email: aulasparticularesdealemaosp@gmail.com
License: MIT
Keywords: cython,color count
Classifier: Development Status :: 4 - Beta
Classifier: Programming Language :: Python :: 3 :: Only
Classifier: Programming Language :: Python :: 3.10
Classifier: Topic :: Software Development :: Libraries :: Python Modules
Classifier: Topic :: Utilities
License-File: LICENSE.rst
Requires-Dist: Cython
Requires-Dist: numpy
